setup.py
gwm_skywalking.egg-info/PKG-INFO
gwm_skywalking.egg-info/SOURCES.txt
gwm_skywalking.egg-info/dependency_links.txt
gwm_skywalking.egg-info/requires.txt
gwm_skywalking.egg-info/top_level.txt
skywalking/__init__.py
skywalking/config.py
skywalking/decorators.py
skywalking/loggings.py
skywalking/agent/__init__.py
skywalking/agent/protocol/__init__.py
skywalking/agent/protocol/grpc.py
skywalking/agent/protocol/http.py
skywalking/agent/protocol/interceptors.py
skywalking/agent/protocol/kafka.py
skywalking/client/__init__.py
skywalking/client/grpc.py
skywalking/client/http.py
skywalking/client/kafka.py
skywalking/plugins/__init__.py
skywalking/plugins/sw_django.py
skywalking/plugins/sw_elasticsearch.py
skywalking/plugins/sw_flask.py
skywalking/plugins/sw_http_server.py
skywalking/plugins/sw_kafka.py
skywalking/plugins/sw_pymongo.py
skywalking/plugins/sw_pymysql.py
skywalking/plugins/sw_rabbitmq.py
skywalking/plugins/sw_redis.py
skywalking/plugins/sw_requests.py
skywalking/plugins/sw_rocketmq.py
skywalking/plugins/sw_tornado.py
skywalking/plugins/sw_urllib3.py
skywalking/plugins/sw_urllib_request.py
skywalking/protocol/__init__.py
skywalking/protocol/browser/BrowserPerf_pb2.py
skywalking/protocol/browser/BrowserPerf_pb2_grpc.py
skywalking/protocol/browser/__init__.py
skywalking/protocol/common/Common_pb2.py
skywalking/protocol/common/Common_pb2_grpc.py
skywalking/protocol/common/__init__.py
skywalking/protocol/language_agent/CLRMetric_pb2.py
skywalking/protocol/language_agent/CLRMetric_pb2_grpc.py
skywalking/protocol/language_agent/JVMMetric_pb2.py
skywalking/protocol/language_agent/JVMMetric_pb2_grpc.py
skywalking/protocol/language_agent/Tracing_pb2.py
skywalking/protocol/language_agent/Tracing_pb2_grpc.py
skywalking/protocol/language_agent/__init__.py
skywalking/protocol/management/Management_pb2.py
skywalking/protocol/management/Management_pb2_grpc.py
skywalking/protocol/management/__init__.py
skywalking/protocol/profile/Profile_pb2.py
skywalking/protocol/profile/Profile_pb2_grpc.py
skywalking/protocol/profile/__init__.py
skywalking/protocol/service_mesh_probe/__init__.py
skywalking/protocol/service_mesh_probe/service_mesh_pb2.py
