Metadata-Version: 2.1
Name: gwm-skywalking
Version: 0.1.0
Summary: Python Agent for Apache SkyWalking Add FastApi RocketMQ Plugins
Home-page: UNKNOWN
Author: licong
Author-email: GW00213211@gwn.cn
License: Apache 2.0
Platform: UNKNOWN
Classifier: Framework :: Flake8
Classifier: License :: OSI Approved :: Apache Software License
Classifier: Operating System :: OS Independent
Classifier: Programming Language :: Python
Classifier: Programming Language :: Python :: 3
Classifier: Programming Language :: Python :: 3.5
Classifier: Programming Language :: Python :: 3.6
Classifier: Programming Language :: Python :: 3.7
Classifier: Programming Language :: Python :: 3.8
Classifier: Topic :: Software Development
